Metadata-Version: 2.1
Name: ultralytics-headless
Version: 8.3.33
Summary: Ultralytics YOLO 🚀 for SOTA object detection, multi-object tracking, instance segmentation, pose estimation and image classification.
Author-email: Glenn Jocher <glenn.jocher@ultralytics.com>, Jing Qiu <jing.qiu@ultralytics.com>
Maintainer-email: Ultralytics <olivier.mirat.om@gmail.com>
License: AGPL-3.0
Project-URL: Homepage, https://ultralytics.com
Project-URL: Source, https://github.com/ultralytics/ultralytics
Project-URL: Documentation, https://docs.ultralytics.com
Project-URL: Bug Reports, https://github.com/ultralytics/ultralytics/issues
Project-URL: Changelog, https://github.com/ultralytics/ultralytics/releases
Keywords: machine-learning,deep-learning,computer-vision,ML,DL,AI,YOLO,YOLOv3,YOLOv5,YOLOv8,YOLOv9,YOLOv10,YOLO11,HUB,Ultralytics
Classifier: Development Status :: 4 - Beta
Classifier: Intended Audience :: Developers
Classifier: Intended Audience :: Education
Classifier: Intended Audience :: Science/Research
Classifier: License :: OSI Approved :: GNU Affero General Public License v3 or later (AGPLv3+)
Classifier: Programming Language :: Python :: 3
Classifier: Programming Language :: Python :: 3.8
Classifier: Programming Language :: Python :: 3.9
Classifier: Programming Language :: Python :: 3.10
Classifier: Programming Language :: Python :: 3.11
Classifier: Programming Language :: Python :: 3.12
Classifier: Topic :: Software Development
Classifier: Topic :: Scientific/Engineering
Classifier: Topic :: Scientific/Engineering :: Artificial Intelligence
Classifier: Topic :: Scientific/Engineering :: Image Recognition
Classifier: Operating System :: POSIX :: Linux
Classifier: Operating System :: MacOS
Classifier: Operating System :: Microsoft :: Windows
Requires-Python: >=3.8
License-File: LICENSE
Requires-Dist: numpy>=1.23.0
Requires-Dist: matplotlib>=3.3.0
Requires-Dist: opencv-python-headless
Requires-Dist: pillow>=7.1.2
Requires-Dist: pyyaml>=5.3.1
Requires-Dist: requests>=2.23.0
Requires-Dist: scipy>=1.4.1
Requires-Dist: torch>=1.8.0
Requires-Dist: torchvision>=0.9.0
Requires-Dist: tqdm>=4.64.0
Requires-Dist: psutil
Requires-Dist: py-cpuinfo
Requires-Dist: pandas>=1.1.4
Requires-Dist: seaborn>=0.11.0
Requires-Dist: ultralytics-thop>=2.0.0
Requires-Dist: numpy<2.0.0; sys_platform == "darwin"
Requires-Dist: torch!=2.4.0,>=1.8.0; sys_platform == "win32"
Provides-Extra: dev
Requires-Dist: ipython; extra == "dev"
Requires-Dist: pytest; extra == "dev"
Requires-Dist: pytest-cov; extra == "dev"
Requires-Dist: coverage[toml]; extra == "dev"
Requires-Dist: mkdocs>=1.6.0; extra == "dev"
Requires-Dist: mkdocs-material>=9.5.9; extra == "dev"
Requires-Dist: mkdocstrings[python]; extra == "dev"
Requires-Dist: mkdocs-jupyter; extra == "dev"
Requires-Dist: mkdocs-redirects; extra == "dev"
Requires-Dist: mkdocs-ultralytics-plugin>=0.1.8; extra == "dev"
Requires-Dist: mkdocs-macros-plugin>=1.0.5; extra == "dev"
Provides-Extra: export
Requires-Dist: onnx>=1.12.0; extra == "export"
Requires-Dist: openvino>=2024.0.0; extra == "export"
Requires-Dist: tensorflow>=2.0.0; extra == "export"
Requires-Dist: tensorflowjs>=3.9.0; extra == "export"
Requires-Dist: keras; extra == "export"
Requires-Dist: flatbuffers<100,>=23.5.26; platform_machine == "aarch64" and extra == "export"
Requires-Dist: numpy==1.23.5; platform_machine == "aarch64" and extra == "export"
Requires-Dist: h5py!=3.11.0; platform_machine == "aarch64" and extra == "export"
Requires-Dist: tensorstore>=0.1.63; (platform_machine == "aarch64" and python_version >= "3.9") and extra == "export"
Requires-Dist: coremltools>=7.0; (platform_system != "Windows" and python_version <= "3.11") and extra == "export"
Requires-Dist: scikit-learn>=1.3.2; (platform_system != "Windows" and python_version <= "3.11") and extra == "export"
Provides-Extra: extra
Requires-Dist: hub-sdk>=0.0.12; extra == "extra"
Requires-Dist: ipython; extra == "extra"
Requires-Dist: albumentations>=1.4.6; extra == "extra"
Requires-Dist: pycocotools>=2.0.7; extra == "extra"
Provides-Extra: logging
Requires-Dist: comet; extra == "logging"
Requires-Dist: tensorboard>=2.13.0; extra == "logging"
Requires-Dist: dvclive>=2.12.0; extra == "logging"
Provides-Extra: solutions
Requires-Dist: shapely>=2.0.0; extra == "solutions"
Requires-Dist: streamlit; extra == "solutions"
